<?xml version="1.0"?>
<!--<!DOCTYPE metadata SYSTEM "http://www.esri.com/metadata/esriprof80.dtd">-->
<metadata xml:lang="en"><Esri><CreaDate>20041005</CreaDate><CreaTime>09294500</CreaTime><SyncOnce>TRUE</SyncOnce><MetaID>{405AF5B3-9E0B-436E-8D97-2E317CA914B4}</MetaID></Esri><idinfo><citation><citeinfo><onlink Sync="TRUE">\\THINKPAD-T40\C$\GISDATA\BrownsPond\GRID-Elevation\Elevation</onlink></citeinfo></citation></idinfo><distInfo><distributor><distorTran><onLineSrc><linkage Sync="TRUE">file://\\THINKPAD-T40\C$\GISDATA\BrownsPond\GRID-Elevation\Elevation</linkage><protocol Sync="TRUE">Local Area Network</protocol></onLineSrc></distorTran></distributor></distInfo><dataqual><lineage><procstep><procdesc Sync="TRUE">Dataset copied.</procdesc><srcused Sync="TRUE">C:\GISDATA\FromOldThinkPad\Browns\BPELE</srcused><date Sync="TRUE">20040926</date><time Sync="TRUE">20245600</time></procstep><procstep><procdesc Sync="TRUE">Dataset copied.</procdesc><srcused Sync="TRUE">C:\GISDATA\BPDATA\Elevation</srcused><date Sync="TRUE">20041005</date><time Sync="TRUE">09294500</time></procstep></lineage></dataqual></metadata>
